poetry_build_compact/__init__.py
poetry_build_compact/plugin.py
poetry_build_compact-1.2.1.dist-info/COPYING
poetry_build_compact-1.2.1.dist-info/COPYING.LESSER
poetry_build_compact-1.2.1.dist-info/METADATA
poetry_build_compact-1.2.1.dist-info/WHEEL
poetry_build_compact-1.2.1.dist-info/entry_points.txt
poetry_build_compact-1.2.1.dist-info/RECORD
