Metadata-Version: 2.1
Name: poetry-build-compact
Version: 1.2.1
Summary: Poetry plugin providing command to compile package into bytecode one
License: LGPL-3.0-only
Author: ZiphyCare LLC
Author-email: support@ziphycare.com
Requires-Python: >=3.7,<4.0
Classifier: License :: OSI Approved :: GNU Lesser General Public License v3 (LGPLv3)
Classifier: Programming Language :: Python :: 3
Classifier: Programming Language :: Python :: 3.7
Classifier: Programming Language :: Python :: 3.8
Classifier: Programming Language :: Python :: 3.9
Classifier: Programming Language :: Python :: 3.10
Classifier: Programming Language :: Python :: 3.11
Classifier: Programming Language :: Python :: 3.12
Requires-Dist: poetry (>=1.5.0,<2.0.0)
